{
  "donors": [
    {
      "phone1_type": "Personal",
      "phone2_type": "home",
      "name": "John Brown 1",
      "type": "individual",
      "org_type": "Individual",
      "org_name": "Individual Business",
      "email": "sample1@gmail.com",
      "phone1": "03119574073",
      "phone2": "03123232321",
      "address": "New York No. 1 Lake Park",
      "id": 1
    },
    {
      "prefix": "Personal",
      "name": "Jim Green",
      "type": "individual",
      "org_type": "Business",
      "org_name": "Business 123",
      "email": "sample1@gmail.com",
      "phone1": "03119574073",
      "phone1_type": "personal",
      "phone2_type": "home",
      "phone2": "03123232323",
      "address": "London No. 1 Lake Park",
      "id": 2
    },
    {
      "id": 3,
      "name": "Joe Black",
      "address": "Sidney No. 1 Lake Park",
      "phone1": "03119574073",
      "phone2": "03123232323",
      "phone1_type": "personal",
      "phone2_type": "home",
      "email": "sample1@gmail.com",
      "type": "individual",
      "contact": "ABC",
      "org_type": "Business",
      "org_name": "Business Org"
    },
    {
      "prefix": "Personal",
      "name": "New Donor",
      "type": "Individual",
      "org_type": "Individual",
      "org_name": "Org 123",
      "email": "administrator@workforcecity.com",
      "phone1": "0211233232",
      "phone1_type": "personal",
      "phone2_type": "home",
      "phone2": "03225786523",
      "address": "village",
      "id": 4
    },
    {
      "prefix": "Personal",
      "name": "New",
      "type": "Individual",
      "org_type": "Organization",
      "org_name": "Org 123",
      "email": "administrator@workforcecity.com",
      "phone1": "0211233232",
      "phone1_type": "personal",
      "phone2_type": "home",
      "phone2": "03225786523",
      "address": "village",
      "id": 5
    },
    {
      "prefix": "Personal",
      "name": "1234",
      "type": "Individual",
      "org_type": "Individual",
      "org_name": "Org 123",
      "phone1_type": "personal",
      "phone2_type": "home",
      "email": "administrator@workforcecity.com",
      "phone1": "0211233232",
      "phone2": "03225786523",
      "address": "village",
      "id": 6
    },
    {
      "prefix": "personal",
      "name": "Sabir",
      "type": "Individual",
      "org_type": "Individual",
      "org_name": "Business 123",
      "phone1_type": "personal",
      "phone2_type": "home",
      "email": "sabir.iiui@gmail.com",
      "phone1": "0211233232",
      "phone2": "03225786523",
      "address": "London No. 1 Lake Park",
      "id": 7
    },
    {
      "prefix": "Personal",
      "name": "D Doner",
      "type": "Individual",
      "org_type": "Organization",
      "org_name": "Business 123",
      "email": "sabir.iiui@gmail.com",
      "phone1": "0211233232",
      "phone2": "03225786523",
      "phone1_type": "personal",
      "phone2_type": "home",
      "address": "London No. 1 Lake Park",
      "id": 8
    }
  ]
}